orbis_unum/__init__.py
orbis_unum/coreutils.py
orbis_unum/main.py
orbis_unum/messages.py
orbis_unum/orbis.py
orbis_unum/templates/index.html
orbis_unum/templates/map.html
orbis_unum-1.2.1.dist-info/LICENSE
orbis_unum-1.2.1.dist-info/METADATA
orbis_unum-1.2.1.dist-info/WHEEL
orbis_unum-1.2.1.dist-info/entry_points.txt
orbis_unum-1.2.1.dist-info/RECORD
