Metadata-Version: 2.1
Name: orbis-unum
Version: 1.2.1
Summary: 🌍 IP Geolocator & Coordinate Mapping tool 📍
Home-page: https://github.com/rly0nheart/orbis-unum
License: MIT
Keywords: mapping,geolocation,reverse-geolocation
Author: Richard Mwewa
Author-email: rly0nheart@duck.com
Requires-Python: >=3.10,<4.0
Classifier: Development Status :: 5 - Production/Stable
Classifier: Intended Audience :: Information Technology
Classifier: License :: OSI Approved :: MIT License
Classifier: Natural Language :: English
Classifier: Operating System :: OS Independent
Classifier: Programming Language :: Python :: 3
Classifier: Programming Language :: Python :: 3.10
Classifier: Programming Language :: Python :: 3.11
Classifier: Programming Language :: Python :: 3.12
Requires-Dist: aiohttp
Requires-Dist: flask
Requires-Dist: jinja2
Requires-Dist: rich
Requires-Dist: rich-argparse
Project-URL: Repository, https://github.com/rly0nheart/orbis-unum
